{"status":0,"data":[{"title":"\n\t\t\t\t\t\t\t从新开帖记录，天涯还是陪伴若干年了。\n\t\t\t\t\t\t","type":"原创精品","url":"http://bbs.tianya.cn/post-45-1826420-1.shtml","author":"重庆飞空","point":"6246","time":"237"},{"title":"\n\t\t\t\t\t\t\t演员变硬汉、硬汉变演员\n\t\t\t\t\t\t","type":"普通帖","url":"http://bbs.tianya.cn/post-45-1829273-1.shtml","author":"山城白酒","point":"21256","time":"644"},{"title":"\n\t\t\t\t\t\t\t幸福地加油\n\t\t\t\t\t\t","type":"普通帖","url":"http://bbs.tianya.cn/post-45-1829401-1.shtml","author":"影弓","point":"7480","time":"428"},{"title":"\n\t\t\t\t\t\t\t求助，家中空调被盗不知道找哪个部门\n\t\t\t\t\t\t","type":"普通帖","url":"http://bbs.tianya.cn/post-45-1829595-1.shtml","author":"刑侦中队长","point":"18","time":"1"},{"title":"\n\t\t\t\t\t\t\t重庆城的老龙门阵---大梁子与新华路\n\t\t\t\t\t\t","type":"普通帖","url":"http://bbs.tianya.cn/post-45-1829594-1.shtml","author":"俺老年痴呆病人","point":"46","time":"13"},{"title":"\n\t\t\t\t\t\t\t醉汉报警后开车去派出所处理纠纷！\n\t\t\t\t\t\t","type":"普通帖","url":"http://bbs.tianya.cn/post-45-1829585-1.shtml","author":"公民监督力推改革","point":"89","time":"1"},{"title":"\n\t\t\t\t\t\t\t华约与北约\n\t\t\t\t\t\t","type":"普通帖","url":"http://bbs.tianya.cn/post-45-1829368-1.shtml","author":"牟勇汽修","point":"2932","time":"214"},{"title":"\n\t\t\t\t\t\t\t我想知道这个美女的信息\n\t\t\t\t\t\t","type":"普通帖","url":"http://bbs.tianya.cn/post-45-1827376-1.shtml","author":"另个城市另个她","point":"1638","time":"8"},{"title":"\n\t\t\t\t\t\t\t开眼看世界，感受各国风土人情\n\t\t\t\t\t\t","type":"普通帖","url":"http://bbs.tianya.cn/post-45-1829561-1.shtml","author":"流浪到重庆X","point":"421","time":"55"},{"title":"\n\t\t\t\t\t\t\t外交部副部长乐玉成谈俄罗斯遭制裁：恐怕没人再信西方所谓“私有财产神圣不可侵犯”。\n\t\t\t\t\t\t","type":"普通帖","url":"http://bbs.tianya.cn/post-45-1829484-1.shtml","author":"公民监督力推改革","point":"434","time":"20"},{"title":"\n\t\t\t\t\t\t\t当机械化遇上信息化和智能化\n\t\t\t\t\t\t","type":"普通帖","url":"http://bbs.tianya.cn/post-45-1829502-1.shtml","author":"渝州老白姓","point":"3544","time":"161"},{"title":"\n\t\t\t\t\t\t\t我也来只说这几句​\n\t\t\t\t\t\t","type":"普通帖","url":"http://bbs.tianya.cn/post-45-1829562-1.shtml","author":"王老大哥2012V","point":"933","time":"101"},{"title":"\n\t\t\t\t\t\t\t呼吁重庆市人民检察院纠正重庆市第三中级人民法院的错案\n\t\t\t\t\t\t","type":"普通帖","url":"http://bbs.tianya.cn/post-45-1822557-1.shtml","author":"飞雨飞茨","point":"1222","time":"113"},{"title":"\n\t\t\t\t\t\t\t中国基建在重庆创造奇迹！山城地铁的通车里程超过500公里\n\t\t\t\t\t\t","type":"普通帖","url":"http://bbs.tianya.cn/post-45-1829590-1.shtml","author":"王老大哥2012V","point":"200","time":"13"},{"title":"\n\t\t\t\t\t\t\t荣昌区2022届高考二轮复习备考教师能力提升培训顺利开展\n\t\t\t\t\t\t","type":"普通帖","url":"http://bbs.tianya.cn/post-45-1829592-1.shtml","author":"ty_118535310","point":"22","time":"1"},{"title":"\n\t\t\t\t\t\t\t三为课堂展风采，扎实教研促成长\n\t\t\t\t\t\t","type":"普通帖","url":"http://bbs.tianya.cn/post-45-1829593-1.shtml","author":"ty_118535310","point":"22","time":"1"},{"title":"\n\t\t\t\t\t\t\t父母很节约，每次看父母不送钱，你们买什么？\n\t\t\t\t\t\t","type":"普通帖","url":"http://bbs.tianya.cn/post-45-1821579-1.shtml","author":"火锅哥哥","point":"4775","time":"146"},{"title":"\n\t\t\t\t\t\t\t一名出租车司机，调侃加夜班的二位码农(转载)\n\t\t\t\t\t\t","type":"普通帖","url":"http://bbs.tianya.cn/post-45-1829591-1.shtml","author":"王老大哥2012V","point":"235","time":"10"},{"title":"\n\t\t\t\t\t\t\t美媒评论：新达成的天然气协议或只具有象征意义\n\t\t\t\t\t\t","type":"普通帖","url":"http://bbs.tianya.cn/post-45-1829553-1.shtml","author":"流浪到重庆X","point":"777","time":"76"},{"title":"\n\t\t\t\t\t\t\t帖子内容，味道完全变了\n\t\t\t\t\t\t","type":"普通帖","url":"http://bbs.tianya.cn/post-45-1829569-1.shtml","author":"燕妈","point":"663","time":"31"},{"title":"\n\t\t\t\t\t\t\t重庆十大女强人。。。(转载)\n\t\t\t\t\t\t","type":"普通帖","url":"http://bbs.tianya.cn/post-45-1829518-1.shtml","author":"王老大哥2012V","point":"1275","time":"24"},{"title":"\n\t\t\t\t\t\t\t重庆四家司法机关都认定代书遗嘱由继承人代书和见证合法有效\n\t\t\t\t\t\t","type":"普通帖","url":"http://bbs.tianya.cn/post-45-1821612-1.shtml","author":"飞雨飞茨","point":"1708","time":"208"},{"title":"\n\t\t\t\t\t\t\t江北城老照片\n\t\t\t\t\t\t","type":"普通帖","url":"http://bbs.tianya.cn/post-45-1826864-1.shtml","author":"越南哥哥","point":"6882","time":"67"},{"title":"\n\t\t\t\t\t\t\t一群多人多号，有脸说别人养号\n\t\t\t\t\t\t","type":"普通帖","url":"http://bbs.tianya.cn/post-45-1820939-1.shtml","author":"乾坤瞳","point":"740","time":"27"},{"title":"\n\t\t\t\t\t\t\t音乐树洞\n\t\t\t\t\t\t","type":"普通帖","url":"http://bbs.tianya.cn/post-45-1829555-1.shtml","author":"fausto","point":"157","time":"8"},{"title":"\n\t\t\t\t\t\t\t我知道重庆不要彩礼的原因了,因为谈恋爱叫耍朋友。\n\t\t\t\t\t\t","type":"普通帖","url":"http://bbs.tianya.cn/post-45-1829584-1.shtml","author":"假十八","point":"167","time":"3"},{"title":"\n\t\t\t\t\t\t\t4月15日起，重庆路内停车收费标准将有这些变化！\n\t\t\t\t\t\t","type":"普通帖","url":"http://bbs.tianya.cn/post-45-1829580-1.shtml","author":"渝北智慧停车","point":"232","time":"2"},{"title":"\n\t\t\t\t\t\t\t疫情下的坚守\n\t\t\t\t\t\t","type":"普通帖","url":"http://bbs.tianya.cn/post-45-1829587-1.shtml","author":"ty_小宝574","point":"90","time":"1"},{"title":"\n\t\t\t\t\t\t\t疑似重庆一检察院领导干部披着马甲在天涯辱骂当事人！\n\t\t\t\t\t\t","type":"普通帖","url":"http://bbs.tianya.cn/post-45-1825083-1.shtml","author":"飞雨飞茨","point":"4559","time":"156"},{"title":"\n\t\t\t\t\t\t\t九命猫娱乐：岁月是把杀猪刀，对女人比男人有时更狠！(转载)\n\t\t\t\t\t\t","type":"普通帖","url":"http://bbs.tianya.cn/post-45-1829576-1.shtml","author":"王老大哥2012V","point":"386","time":"27"},{"title":"\n\t\t\t\t\t\t\t民间备忘\n\t\t\t\t\t\t","type":"普通帖","url":"http://bbs.tianya.cn/post-45-1829552-1.shtml","author":"老天丫2000","point":"215","time":"7"},{"title":"\n\t\t\t\t\t\t\t乡村记忆，小小说《一架纸飞机》\n\t\t\t\t\t\t","type":"普通帖","url":"http://bbs.tianya.cn/post-45-1829482-1.shtml","author":"肖福祥","point":"112","time":"5"},{"title":"\n\t\t\t\t\t\t\t关长山隧道车祸 过往车辆请慢行\n\t\t\t\t\t\t","type":"普通帖","url":"http://bbs.tianya.cn/post-45-1829589-1.shtml","author":"西餐淘淘","point":"140","time":"0"},{"title":"\n\t\t\t\t\t\t\t有护栏被撞 大家开车小心\n\t\t\t\t\t\t","type":"普通帖","url":"http://bbs.tianya.cn/post-45-1829588-1.shtml","author":"西餐淘淘","point":"98","time":"0"},{"title":"\n\t\t\t\t\t\t\t刘镇玮和儿子的美食日记\n\t\t\t\t\t\t","type":"推荐话题","url":"http://bbs.tianya.cn/post-45-1819031-1.shtml","author":"石猴731","point":"6536","time":"155"},{"title":"\n\t\t\t\t\t\t\t恳请中央第十三督导组彻查重庆四家司法机关承认错案却不纠正\n\t\t\t\t\t\t","type":"普通帖","url":"http://bbs.tianya.cn/post-45-1825754-1.shtml","author":"飞雨飞茨","point":"7382","time":"77"},{"title":"\n\t\t\t\t\t\t\t石桥铺的公交车站台上，设置不锈钢条凳了\n\t\t\t\t\t\t","type":"普通帖","url":"http://bbs.tianya.cn/post-45-1825230-1.shtml","author":"王老大哥2012V","point":"2148","time":"28"},{"title":"\n\t\t\t\t\t\t\t美国在日本扔下原子弹后至今日本对美国俯首称臣说明了什么？\n\t\t\t\t\t\t","type":"普通帖","url":"http://bbs.tianya.cn/post-45-1829581-1.shtml","author":"公民监督力推改革","point":"182","time":"13"},{"title":"\n\t\t\t\t\t\t\t一小学生被溅一身水，报警后司机被罚200 。\n\t\t\t\t\t\t","type":"普通帖","url":"http://bbs.tianya.cn/post-45-1829583-1.shtml","author":"公民监督力推改革","point":"131","time":"3"},{"title":"\n\t\t\t\t\t\t\t触目惊心！\n\t\t\t\t\t\t","type":"普通帖","url":"http://bbs.tianya.cn/post-45-1829586-1.shtml","author":"公民监督力推改革","point":"157","time":"0"},{"title":"\n\t\t\t\t\t\t\t差速器在双发动机动力协调输出中的应用(转载)\n\t\t\t\t\t\t","type":"普通帖","url":"http://bbs.tianya.cn/post-45-1822953-1.shtml","author":"autud","point":"686","time":"48"},{"title":"\n\t\t\t\t\t\t\t地名的悲哀和文化的衰落！\n\t\t\t\t\t\t","type":"普通帖","url":"http://bbs.tianya.cn/post-45-1829440-1.shtml","author":"纯粹汉语","point":"601","time":"17"},{"title":"\n\t\t\t\t\t\t\t不敏感的小众信息\n\t\t\t\t\t\t","type":"普通帖","url":"http://bbs.tianya.cn/post-45-1826509-1.shtml","author":"对花饮醉","point":"14520","time":"359"},{"title":"\n\t\t\t\t\t\t\t温带四季，看看你们那里的念春图\n\t\t\t\t\t\t","type":"普通帖","url":"http://bbs.tianya.cn/post-45-1829582-1.shtml","author":"正大光明Q","point":"84","time":"0"},{"title":"\n\t\t\t\t\t\t\t警示！重庆发布维护消费公平的十大典型案例。。。\n\t\t\t\t\t\t","type":"普通帖","url":"http://bbs.tianya.cn/post-45-1829575-1.shtml","author":"王老大哥2012V","point":"172","time":"6"},{"title":"\n\t\t\t\t\t\t\t关注重庆公交司机\n\t\t\t\t\t\t","type":"普通帖","url":"http://bbs.tianya.cn/post-45-1820164-1.shtml","author":"夜闯隔壁寡妇村","point":"1247","time":"29"},{"title":"\n\t\t\t\t\t\t\t呼吁江北区法院审委会已承认的数千件错案的受害者拿起法律武器维权\n\t\t\t\t\t\t","type":"普通帖","url":"http://bbs.tianya.cn/post-45-1822556-1.shtml","author":"飞雨飞茨","point":"1491","time":"155"},{"title":"\n\t\t\t\t\t\t\t一个重庆平民的永难明白：为什么人类的两次世界大战都在欧洲爆发？并且而\n\t\t\t\t\t\t","type":"普通帖","url":"http://bbs.tianya.cn/post-45-1829385-1.shtml","author":"王老大哥2012V","point":"1470","time":"68"},{"title":"\n\t\t\t\t\t\t\t请江北区法院纠正审委会都承认的数千件错案\n\t\t\t\t\t\t","type":"普通帖","url":"http://bbs.tianya.cn/post-45-1821851-1.shtml","author":"飞雨飞茨","point":"1657","time":"160"},{"title":"\n\t\t\t\t\t\t\t想要在照母山置业，求大家给点意见！\n\t\t\t\t\t\t","type":"普通帖","url":"http://bbs.tianya.cn/post-45-1829511-1.shtml","author":"奋斗青年one","point":"619","time":"16"},{"title":"\n\t\t\t\t\t\t\t为公交志愿者点赞\n\t\t\t\t\t\t","type":"普通帖","url":"http://bbs.tianya.cn/post-45-1829200-1.shtml","author":"夜静思涛","point":"87","time":"3"},{"title":"\n\t\t\t\t\t\t\t《他》\n\t\t\t\t\t\t","type":"普通帖","url":"http://bbs.tianya.cn/post-45-1829579-1.shtml","author":"梁州牧","point":"74","time":"0"},{"title":"\n\t\t\t\t\t\t\t重拳出击，专项整治持续到今年年底。\n\t\t\t\t\t\t","type":"普通帖","url":"http://bbs.tianya.cn/post-45-1829577-1.shtml","author":"公民监督力推改革","point":"125","time":"0"},{"title":"\n\t\t\t\t\t\t\t电动轿车多线快充与分线快充(转载)\n\t\t\t\t\t\t","type":"普通帖","url":"http://bbs.tianya.cn/post-45-1822976-1.shtml","author":"autud","point":"556","time":"26"},{"title":"\n\t\t\t\t\t\t\t人工智能算力达到国际先进水平。\n\t\t\t\t\t\t","type":"普通帖","url":"http://bbs.tianya.cn/post-45-1829573-1.shtml","author":"公民监督力推改革","point":"76","time":"1"},{"title":"\n\t\t\t\t\t\t\t呼吁重庆市的数千名错案当事人向中央控告江北区法院渎职\n\t\t\t\t\t\t","type":"普通帖","url":"http://bbs.tianya.cn/post-45-1823078-1.shtml","author":"飞雨飞茨","point":"2500","time":"128"},{"title":"\n\t\t\t\t\t\t\t重庆的四川美术学院，恢复中学招生，旨在加强美术特长生培养\n\t\t\t\t\t\t","type":"普通帖","url":"http://bbs.tianya.cn/post-45-1829528-1.shtml","author":"王老大哥2012V","point":"514","time":"25"},{"title":"\n\t\t\t\t\t\t\t终于明白 物管公司 可以那么肆无忌惮的胡作非为\n\t\t\t\t\t\t","type":"普通帖","url":"http://bbs.tianya.cn/post-45-1829450-1.shtml","author":"liubaid","point":"542","time":"7"},{"title":"\n\t\t\t\t\t\t\t秋水长天 三岔路口 红绿灯能不能优化？？？？\n\t\t\t\t\t\t","type":"普通帖","url":"http://bbs.tianya.cn/post-45-1829527-1.shtml","author":"liubaid","point":"214","time":"9"},{"title":"\n\t\t\t\t\t\t\t波音公司官方微博发文向东航MU5735航班坠机事故遇难者致哀。\n\t\t\t\t\t\t","type":"普通帖","url":"http://bbs.tianya.cn/post-45-1829574-1.shtml","author":"公民监督力推改革","point":"77","time":"0"},{"title":"\n\t\t\t\t\t\t\t2022年清明节放假安排如下。\n\t\t\t\t\t\t","type":"普通帖","url":"http://bbs.tianya.cn/post-45-1829572-1.shtml","author":"公民监督力推改革","point":"213","time":"0"},{"title":"\n\t\t\t\t\t\t\t国家税务总局重庆市税务局杨亲家还我钱！\n\t\t\t\t\t\t","type":"普通帖","url":"http://bbs.tianya.cn/post-45-1825409-1.shtml","author":"姚川电器","point":"3411","time":"47"},{"title":"\n\t\t\t\t\t\t\t我请求重庆市政府对我国家赔偿！\n\t\t\t\t\t\t","type":"普通帖","url":"http://bbs.tianya.cn/post-45-1825274-1.shtml","author":"姚川电器","point":"4983","time":"122"},{"title":"\n\t\t\t\t\t\t\t好久没谈重庆房价了，今天来说说。\n\t\t\t\t\t\t","type":"推荐话题","url":"http://bbs.tianya.cn/post-45-1828665-1.shtml","author":"工科硕士没文化","point":"48662","time":"554"},{"title":"\n\t\t\t\t\t\t\t为什么雾都重庆成为十大宜居城市之一\n\t\t\t\t\t\t","type":"普通帖","url":"http://bbs.tianya.cn/post-45-1826400-1.shtml","author":"彩云雾绕","point":"9930","time":"396"},{"title":"\n\t\t\t\t\t\t\t西安、杭州因为正确的人才落户政策，正甩开重庆\n\t\t\t\t\t\t","type":"普通帖","url":"http://bbs.tianya.cn/post-45-1826951-1.shtml","author":"渝州老白姓","point":"26512","time":"515"},{"title":"\n\t\t\t\t\t\t\t重庆市公安局警察待遇低吗？\n\t\t\t\t\t\t","type":"普通帖","url":"http://bbs.tianya.cn/post-45-1829381-1.shtml","author":"ty_姚川电器","point":"1324","time":"18"},{"title":"\n\t\t\t\t\t\t\t明天约见阳光。\n\t\t\t\t\t\t","type":"普通帖","url":"http://bbs.tianya.cn/post-45-1829567-1.shtml","author":"公民监督力推改革","point":"114","time":"5"},{"title":"\n\t\t\t\t\t\t\t道格拉斯·麦克阿瑟主持了对日本的受降仪式并代表同盟国签字。\n\t\t\t\t\t\t","type":"普通帖","url":"http://bbs.tianya.cn/post-45-1829570-1.shtml","author":"公民监督力推改革","point":"91","time":"5"},{"title":"\n\t\t\t\t\t\t\t一分院明星检察官王雪花确认了错案，10个区县错案受害者申冤的机会来了\n\t\t\t\t\t\t","type":"普通帖","url":"http://bbs.tianya.cn/post-45-1826889-1.shtml","author":"飞雨飞茨","point":"1591","time":"108"},{"title":"\n\t\t\t\t\t\t\t雨后重庆美如仙境！\n\t\t\t\t\t\t","type":"普通帖","url":"http://bbs.tianya.cn/post-45-1829557-1.shtml","author":"公民监督力推改革","point":"263","time":"2"},{"title":"\n\t\t\t\t\t\t\t中庸是社会的底线\n\t\t\t\t\t\t","type":"普通帖","url":"http://bbs.tianya.cn/post-45-1829565-1.shtml","author":"问天再封50年","point":"189","time":"4"},{"title":"\n\t\t\t\t\t\t\t安全出行，从我做起。\n\t\t\t\t\t\t","type":"普通帖","url":"http://bbs.tianya.cn/post-45-1829568-1.shtml","author":"公民监督力推改革","point":"78","time":"1"},{"title":"\n\t\t\t\t\t\t\t倚天随想\n\t\t\t\t\t\t","type":"普通帖","url":"http://bbs.tianya.cn/post-45-1829485-1.shtml","author":"ty_张楠546","point":"184","time":"3"},{"title":"\n\t\t\t\t\t\t\t马路当库房，交巡警为何不管？\n\t\t\t\t\t\t","type":"黑色幽默","url":"http://bbs.tianya.cn/post-45-1829231-1.shtml","author":"纷飞绝泪","point":"1328","time":"28"},{"title":"\n\t\t\t\t\t\t\t就说这几句\n\t\t\t\t\t\t","type":"普通帖","url":"http://bbs.tianya.cn/post-45-1829543-1.shtml","author":"钢铁豌豆","point":"882","time":"54"},{"title":"\n\t\t\t\t\t\t\t韩红爱心协会向吉林捐款500万！\n\t\t\t\t\t\t","type":"普通帖","url":"http://bbs.tianya.cn/post-45-1829563-1.shtml","author":"公民监督力推改革","point":"55","time":"1"},{"title":"\n\t\t\t\t\t\t\t在追悼日时，日本不点名是谁扔下了原子弹。\n\t\t\t\t\t\t","type":"普通帖","url":"http://bbs.tianya.cn/post-45-1829558-1.shtml","author":"公民监督力推改革","point":"271","time":"15"},{"title":"\n\t\t\t\t\t\t\t《围城》里的人，没有一个是完美的，也没有一个不是被虚荣心或虚伪包裹着的。\n\t\t\t\t\t\t","type":"普通帖","url":"http://bbs.tianya.cn/post-45-1829566-1.shtml","author":"公民监督力推改革","point":"97","time":"2"},{"title":"\n\t\t\t\t\t\t\t东航飞行事故客机第二个黑匣子已找到。\n\t\t\t\t\t\t","type":"普通帖","url":"http://bbs.tianya.cn/post-45-1829564-1.shtml","author":"公民监督力推改革","point":"136","time":"1"}]}